mylib/numerical_method.py
mynumericallib-1.0.0.dist-info/METADATA
mynumericallib-1.0.0.dist-info/WHEEL
mynumericallib-1.0.0.dist-info/top_level.txt
mynumericallib-1.0.0.dist-info/RECORD
