Metadata-Version: 2.1
Name: mynumericallib
Version: 1.0.0
Summary: mylib
Home-page: https://github.com/hyxnmin/abc
Download-URL: https://github.com/hyxnmin/abc/defg.zip
Author: hmpark
License: UNKNOWN
Platform: UNKNOWN
Classifier: Programming Language :: Python :: 3
